polyants/__init__.py
polyants/internal/__init__.py
polyants/internal/logger.py
polyants/polyhub/__init__.py
polyants/polyhub/constants.py
polyants/polyhub/enums.py
polyants/polyhub/exceptions.py
polyants/polyhub/functions/__init__.py
polyants/polyhub/functions/text.py
polyants/polyhub/grpc/__init__.py
polyants/polyhub/grpc/origincrypto_pb2.py
polyants/polyhub/grpc/origincrypto_pb2.pyi
polyants/polyhub/grpc/origincrypto_pb2_grpc.py
polyants/polyhub/grpc/originhttp_pb2.py
polyants/polyhub/grpc/originhttp_pb2.pyi
polyants/polyhub/grpc/originhttp_pb2_grpc.py
polyants/polyhub/helpers/__init__.py
polyants/polyhub/helpers/adapters.py
polyants/polyhub/helpers/common.py
polyants/polyhub/helpers/crypto.py
polyants/polyhub/helpers/data.py
polyants/polyhub/helpers/db.py
polyants/polyhub/helpers/errors.py
polyants/polyhub/helpers/gql.py
polyants/polyhub/helpers/grpcapi.py
polyants/polyhub/helpers/http.py
polyants/polyhub/helpers/io.py
polyants/polyhub/helpers/mappings.py
polyants/polyhub/helpers/redis.py
polyants/polyhub/helpers/reporting.py
polyants/polyhub/helpers/sqlapi.py
polyants/polyhub/helpers/templater.py
polyants/polyhub/helpers/translit.py
polyants/polyhub/helpers/viapi.py
polyants/polyhub/helpers/viasync.py
polyants-0.12a0.dist-info/METADATA
polyants-0.12a0.dist-info/WHEEL
polyants-0.12a0.dist-info/RECORD
