Metadata-Version: 2.3
Name: polyants
Version: 0.12a0
Summary: POLYHUB system helpers
License: MPL-2.0
Keywords: tools,helpers
Author: pymancer
Author-email: pymancer@gmail.com
Requires-Python: >=3.9,<3.13
Classifier: Development Status :: 3 - Alpha
Classifier: Environment :: Console
Classifier: Intended Audience :: Information Technology
Classifier: License :: OSI Approved
Classifier: License :: OSI Approved :: Mozilla Public License 2.0 (MPL 2.0)
Classifier: Operating System :: OS Independent
Classifier: Programming Language :: Python :: 3
Classifier: Programming Language :: Python :: 3.9
Classifier: Programming Language :: Python :: 3.10
Classifier: Programming Language :: Python :: 3.11
Classifier: Programming Language :: Python :: 3.12
Classifier: Topic :: Database
Classifier: Topic :: Software Development :: Libraries
Requires-Dist: Jinja2 (>=2)
Requires-Dist: MarkupSafe (>=2)
Requires-Dist: PyJWT (>=2,<3)
Requires-Dist: aiohttp (>=3,<4)
Requires-Dist: cryptography (>=43)
Requires-Dist: gql (>=2,<4)
Requires-Dist: grpcio (>=1.44.0,<1.65)
Requires-Dist: hiredis (>=3,<4)
Requires-Dist: httpx (>=0,<1)
Requires-Dist: jsqlib (>=0,<1)
Requires-Dist: pathvalidate (>=3,<4)
Requires-Dist: protobuf (>=4,<6)
Requires-Dist: psycopg2-binary (>=2,<3)
Requires-Dist: pyodbc (>=5,<6)
Requires-Dist: pysmb (>=1.2.11,<2.0.0)
Requires-Dist: python-dotenv (>=1,<2)
Requires-Dist: requests (>=2,<3)
Requires-Dist: requests-toolbelt (>=1,<2)
Requires-Dist: sqlparse (>=0,<1)
Requires-Dist: walrus (>=0,<1)
Project-URL: Documentation, https://gitlab.com/ru-r5/polyants/-/wikis/home
Project-URL: Homepage, https://gitlab.com/ru-r5/polyants
Project-URL: Repository, https://gitlab.com/ru-r5/polyants
